gerg_podaac_data_access/__init__.py
gerg_podaac_data_access/auth.py
gerg_podaac_data_access/client.py
gerg_podaac_data_access/models.py
gerg_podaac_data_access/setup_auth.py
gerg_podaac_data_access-0.1.0.dist-info/METADATA
gerg_podaac_data_access-0.1.0.dist-info/WHEEL
gerg_podaac_data_access-0.1.0.dist-info/RECORD
