Metadata-Version: 2.3
Name: gerg_podaac_data_access
Version: 0.1.0
Summary: 
Author: Alec Krueger
Author-email: Alecmkrueger@tamu.edu
Requires-Python: >=3.12,<4.0
Classifier: Programming Language :: Python :: 3
Classifier: Programming Language :: Python :: 3.12
Classifier: Programming Language :: Python :: 3.13
Requires-Dist: notebook (>=7.3.3,<8.0.0)
Requires-Dist: podaac-data-subscriber (>=1.15.2,<2.0.0)
Requires-Dist: xarray (>=2025.3.1,<2026.0.0)
